{
  "generated_at_utc": "2026-06-10T11:06:08Z",
  "profile": "c",
  "reference_profile": "Momentum v2 Display C handoff: C1/C2/C3",
  "screens": [
    {
      "capture": "docs\\browser-qa\\next-handoff\\latest\\next-overview.png",
      "capture_size": [
        1440,
        3905
      ],
      "error": "",
      "missing_text": [],
      "nonblank": true,
      "ok": true,
      "reference": "C:\\Users\\meiri\\momentum and flow\\momentum v2\\design_handoff_momentum_v2\\media\\screens\\C1-pillarstack-heatmap.png",
      "reference_exists": true,
      "reference_size": [
        1440,
        2911
      ],
      "required_text": [
        "The composite, dissected",
        "State changes",
        "Bullish cohort"
      ],
      "rms": 48.7468,
      "screen": "overview",
      "similarity": 0.8088
    },
    {
      "capture": "docs\\browser-qa\\next-handoff\\latest\\next-deepdive.png",
      "capture_size": [
        1440,
        2021
      ],
      "error": "",
      "missing_text": [],
      "nonblank": true,
      "ok": true,
      "reference": "C:\\Users\\meiri\\momentum and flow\\momentum v2\\design_handoff_momentum_v2\\media\\screens\\C2-pillarstack-waterfall.png",
      "reference_exists": true,
      "reference_size": [
        1440,
        1526
      ],
      "required_text": [
        "The composite, built pillar by pillar",
        "FOCUS",
        "State machine"
      ],
      "rms": 41.3649,
      "screen": "deepdive",
      "similarity": 0.8378
    },
    {
      "capture": "docs\\browser-qa\\next-handoff\\latest\\next-rotation.png",
      "capture_size": [
        1440,
        1880
      ],
      "error": "",
      "missing_text": [],
      "nonblank": true,
      "ok": true,
      "reference": "C:\\Users\\meiri\\momentum and flow\\momentum v2\\design_handoff_momentum_v2\\media\\screens\\C3-pillarstack-rotation.png",
      "reference_exists": true,
      "reference_size": [
        1440,
        1790
      ],
      "required_text": [
        "The rotation map",
        "The flow river",
        "Flow internals"
      ],
      "rms": 37.6224,
      "screen": "rotation",
      "similarity": 0.8525
    }
  ],
  "url": "http://127.0.0.1:3100/?presentation=c&qa=shots"
}
